package_jmsierra_fff/__init__.py
package_jmsierra_fff/_dividir.py
package_jmsierra_fff/_multiplicar.py
package_jmsierra_fff/_restar.py
package_jmsierra_fff/_sumar.py
package_jmsierra_fff-0.4.0.dist-info/LICENSE
package_jmsierra_fff-0.4.0.dist-info/METADATA
package_jmsierra_fff-0.4.0.dist-info/WHEEL
package_jmsierra_fff-0.4.0.dist-info/RECORD
