Metadata-Version: 2.1
Name: package-jmsierra-fff
Version: 0.4.0
Summary: Es un proyecto de prueba
Home-page: https://example.com
License: MIT
Keywords: packaging,poetry
Author: Mauricio Sierra
Maintainer: Developers
Maintainer-email: mauricio@gmail.com
Requires-Python: >=3.10,<4.0
Classifier: Development Status :: 5 - Production/Stable
Classifier: Intended Audience :: Developers
Classifier: Intended Audience :: Science/Research
Classifier: License :: OSI Approved :: BSD License
Classifier: License :: OSI Approved :: MIT License
Classifier: Programming Language :: C
Classifier: Programming Language :: Python
Classifier: Programming Language :: Python :: 3
Classifier: Programming Language :: Python :: 3.10
Classifier: Programming Language :: Python :: 3.11
Requires-Dist: numpy (>=1.24.2,<2.0.0)
Requires-Dist: pandas (>=2.0.0,<3.0.0)
Requires-Dist: polars (>=0.17.0,<0.18.0)
Requires-Dist: requests (>=2.28.2,<3.0.0)
Project-URL: Documentation, https://readthedocs.org
Project-URL: Repository, https://github.com
